<annotation>
	<folder>my-project-name</folder>
	<filename>303.jpg</filename>
	<path>/my-project-name/303.jpg</path>
	<source>
		<database>Unspecified</database>
	</source>
	<size>
		<width>800</width>
		<height>533</height>
		<depth>3</depth>
	</size>
	<object>
		<name>RedRose</name>
		<pose>Unspecified</pose>
		<truncated>Unspecified</truncated>
		<difficult>Unspecified</difficult>
		<bndbox>
			<xmin>210</xmin>
			<ymin>74</ymin>
			<xmax>717</xmax>
			<ymax>495</ymax>
		</bndbox>
	</object>
</annotation>